crow_kit/__init__.py
crow_kit/core.py
crow_kit/general_wrapper.js
crow_kit/table_wrapper.js
crow_kit/external_files/css/st.action-panel.css
crow_kit/external_files/js/jquery-3.7.1.min.js
crow_kit/external_files/js/st.action-panel.js
crow_kit/external_files/js/sweetalert2.all.min.js
crow_kit-0.3.2.dist-info/licenses/LICENSE
crow_kit-0.3.2.dist-info/METADATA
crow_kit-0.3.2.dist-info/WHEEL
crow_kit-0.3.2.dist-info/top_level.txt
crow_kit-0.3.2.dist-info/RECORD
